skais_mapper/__about__.py
skais_mapper/__init__.py
skais_mapper/__main__.py
skais_mapper/_compat.py
skais_mapper/_torch_stub.py
skais_mapper/configure.py
skais_mapper/cosmology.py
skais_mapper/data.py
skais_mapper/generate.py
skais_mapper/metrics.py
skais_mapper/plotting.py
skais_mapper/profile.py
skais_mapper/raytrace.c
skais_mapper/raytrace.cpython-311-x86_64-linux-gnu.so
skais_mapper/rotations.py
skais_mapper/simobjects.py
skais_mapper/configs/__init__.py
skais_mapper/illustris/__init__.py
skais_mapper/illustris/groupcat.py
skais_mapper/illustris/snapshots.py
skais_mapper/illustris/util.py
skais_mapper/utils/__init__.py
skais_mapper/utils/colors.py
skais_mapper/utils/config.py
skais_mapper/utils/helper.py
skais_mapper/utils/primes.py
tests/__init__.py
tests/conftest.py
tests/test_configure.py
tests/test_cosmology.py
tests/test_data.py
tests/test_generate.py
tests/test_illustris_util.py
tests/test_metrics.py
tests/test_plotting.py
tests/test_profile.py
tests/test_rotations.py
tests/test_simobjects.py
tests/test_utils.py
skais_mapper-0.1.16.dist-info/METADATA
skais_mapper-0.1.16.dist-info/WHEEL
skais_mapper-0.1.16.dist-info/entry_points.txt
skais_mapper-0.1.16.dist-info/top_level.txt
skais_mapper-0.1.16.dist-info/RECORD
skais_mapper-0.1.16.dist-info/licenses/LICENSE
