Metadata-Version: 2.4
Name: skais-mapper
Version: 0.1.16
Summary: A framework for generating deep-learning SKA radio telescope & cosmological hydrodynamical simulation data
Author-email: Philipp Denzel <phdenzel@gmail.com>
Maintainer-email: Philipp Denzel <phdenzel@gmail.com>
License-Expression: GPL-3.0-or-later
Project-URL: Documentation, https://github.com/phdenzel/skais-mapper#readme
Project-URL: Homepage, https://github.com/phdenzel/skais-mapper
Project-URL: Repository, https://github.com/phdenzel/skais-mapper.git
Project-URL: Issues, https://github.com/phdenzel/skais-mapper/issues
Keywords: cosmological simulations,illustris-tng,radio mocks
Classifier: Development Status :: 4 - Beta
Classifier: Programming Language :: Python
Classifier: Programming Language :: Python :: 3.10
Classifier: Programming Language :: Python :: 3.11
Classifier: Programming Language :: Python :: 3.12
Classifier: Programming Language :: Python :: 3.13
Classifier: Programming Language :: Cython
Classifier: Programming Language :: Python :: Implementation :: CPython
Classifier: Operating System :: Unix
Classifier: Operating System :: POSIX :: Linux
Classifier: Operating System :: MacOS
Classifier: Topic :: Scientific/Engineering :: Image Processing
Classifier: Topic :: Scientific/Engineering :: Astronomy
Requires-Python: >=3.10
License-File: LICENSE
Requires-Dist: numpy
Requires-Dist: scipy
Requires-Dist: tqdm
Requires-Dist: astropy
Requires-Dist: h5py
Requires-Dist: Pillow
Requires-Dist: matplotlib
Requires-Dist: gitpython
Requires-Dist: chuchichaestli>=0.2.9
Requires-Dist: hydra-core>=1.3.2
Provides-Extra: nn
Requires-Dist: torch>=2.7.1; extra == "nn"
Provides-Extra: dev
Requires-Dist: pytest>=8.3.5; extra == "dev"
Requires-Dist: pytest-cov>=5.0.0; extra == "dev"
Requires-Dist: ruff>=0.12.5; extra == "dev"
Provides-Extra: docs
Requires-Dist: mkdocs>=1.6.1; extra == "docs"
Requires-Dist: mkdocs-api-autonav>=0.3.0; extra == "docs"
Requires-Dist: mkdocs-material>=9.6.16; extra == "docs"
Requires-Dist: mkdocstrings[python]>=0.30.0; extra == "docs"
Dynamic: license-file
